cuegen.py
cueparser.py
cueparser-1.3.3.dist-info/licenses/LICENSE
cueparser-1.3.3.dist-info/METADATA
cueparser-1.3.3.dist-info/WHEEL
cueparser-1.3.3.dist-info/entry_points.txt
cueparser-1.3.3.dist-info/top_level.txt
cueparser-1.3.3.dist-info/RECORD
